varfilter/__init__.py
varfilter/filter.py
varfilter/types.py
varfilter/varfilter.py
varfilter-1.0.0a10.dist-info/LICENSE
varfilter-1.0.0a10.dist-info/METADATA
varfilter-1.0.0a10.dist-info/WHEEL
varfilter-1.0.0a10.dist-info/top_level.txt
varfilter-1.0.0a10.dist-info/RECORD
