Metadata-Version: 2.1
Name: varfilter
Version: 1.0.0a10
Summary: filtra variables de distintas fuentes
Home-page: https://github.com/gomibaya/pyVarfilter/
Author: Esteban Barón
Author-email: esteban@gominet.net
License: UNKNOWN
Platform: UNKNOWN
Classifier: Development Status :: 3 - Alpha
Classifier: Programming Language :: Python :: 3
Classifier: Programming Language :: Python :: 3 :: Only
Classifier: Programming Language :: Python :: 3.6
Classifier: Programming Language :: Python :: 3.7
Classifier: Programming Language :: Python :: 3.8
Classifier: License :: OSI Approved :: MIT License
Classifier: Operating System :: OS Independent
Classifier: Natural Language :: Spanish
Requires-Python: >=3.6
